<?xml version="1.0" encoding="UTF-8" standalone="yes"?><response><comMsgHeader><errMsg>NORMAL SERVICE.</errMsg><returnCode>00</returnCode></comMsgHeader><msgHeader><queryTime>2020-10-02 17:14:09.567</queryTime><resultCode>0</resultCode><resultMessage>정상적으로 처리되었습니다.</resultMessage></msgHeader><msgBody><busRouteStationList><centerYn>N</centerYn><districtCd>2</districtCd><mobileNo> 04046</mobileNo><regionName>수원</regionName><stationId>203000023</stationId><stationName>삼성전자중앙문</stationName><x>127.0486667</x><y>37.2593833</y><stationSeq>1</stationSeq><turnYn>N</turnYn></busRouteStationList><busRouteStationList><centerYn>N</centerYn><districtCd>2</districtCd><regionName>수원</regionName><stationId>277102595</stationId><stationName>매원고삼거리(경유)</stationName><x>127.0522333</x><y>37.2657167</y><stationSeq>2</stationSeq><turnYn>N</turnYn></busRouteStationList><busRouteStationList><centerYn>N</centerYn><districtCd>2</districtCd><mobileNo> 04071</mobileNo><regionName>수원</regionName><stationId>203000116</stationId><stationName>금성아파트.한국2차아파트</stationName><x>127.05625</x><y>37.26735</y><stationSeq>3</stationSeq><turnYn>N</turnYn></busRouteStationList><busRouteStationList><centerYn>N</centerYn><districtCd>2</districtCd><mobileNo> 04087</mobileNo><regionName>수원</regionName><stationId>203000071</stationId><stationName>광교호수공원입구.원천교사거리</stationName><x>127.0596</x><y>37.2709333</y><stationSeq>4</stationSeq><turnYn>N</turnYn></busRouteStationList><busRouteStationList><centerYn>N</centerYn><districtCd>2</districtCd><mobileNo> 04056</mobileNo><regionName>수원</regionName><stationId>203000069</stationId><stationName>KT동수원지사</stationName><x>127.0511</x><y>37.2735833</y><stationSeq>5</stationSeq><turnYn>N</turnYn></busRouteStationList><busRouteStationList><centerYn>N</centerYn><districtCd>2</districtCd><mobileNo> 04286</mobileNo><regionName>수원</regionName><stationId>203000294</stationId><stationName>소화초등학교</stationName><x>127.0519833</x><y>37.2779667</y><stationSeq>6</stationSeq><turnYn>N</turnYn></busRouteStationList><busRouteStationList><centerYn>N</centerYn><districtCd>2</districtCd><mobileNo> 04396</mobileNo><regionName>수원</regionName><stationId>203000399</stationId><stationName>광교중앙.아주대역환승센터</stationName><x>127.0518833</x><y>37.2884833</y><stationSeq>7</stationSeq><turnYn>N</turnYn></busRouteStationList><busRouteStationList><centerYn>N</centerYn><districtCd>2</districtCd><mobileNo> 04186</mobileNo><regionName>수원</regionName><stationId>203000042</stationId><stationName>푸르지오월드마크.차세대융합기술연구원</stationName><x>127.0474167</x><y>37.2924333</y><stationSeq>8</stationSeq><turnYn>N</turnYn></busRouteStationList><busRouteStationList><centerYn>N</centerYn><districtCd>2</districtCd><regionName>수원</regionName><stationId>277103382</stationId><stationName>동수원TG(경유)</stationName><x>127.0470833</x><y>37.2971</y><stationSeq>9</stationSeq><turnYn>N</turnYn></busRouteStationList><busRouteStationList><centerYn>N</centerYn><districtCd>2</districtCd><regionName>수원</regionName><stationId>277103691</stationId><stationName>광교(경유)</stationName><x>127.0789167</x><y>37.2931667</y><stationSeq>10</stationSeq><turnYn>N</turnYn></busRouteStationList><busRouteStationList><centerYn>N</centerYn><districtCd>2</districtCd><regionName>용인</regionName><stationId>277103231</stationId><stationName>신갈JC(경유)</stationName><x>127.1031167</x><y>37.2898</y><stationSeq>11</stationSeq><turnYn>N</turnYn></busRouteStationList><busRouteStationList><centerYn>N</centerYn><districtCd>2</districtCd><regionName>용인</regionName><stationId>277103443</stationId><stationName>죽전(경유)</stationName><x>127.1038167</x><y>37.3266333</y><stationSeq>12</stationSeq><turnYn>N</turnYn></busRouteStationList><busRouteStationList><centerYn>N</centerYn><districtCd>2</districtCd><regionName>성남</regionName><stationId>277103386</stationId><stationName>서울TG(경유)</stationName><x>127.1043333</x><y>37.3649667</y><stationSeq>13</stationSeq><turnYn>N</turnYn></busRouteStationList><busRouteStationList><centerYn>N</centerYn><districtCd>2</districtCd><regionName>성남</regionName><stationId>277103151</stationId><stationName>판교IC(경유)</stationName><x>127.1006167</x><y>37.3986333</y><stationSeq>14</stationSeq><turnYn>N</turnYn></busRouteStationList><busRouteStationList><centerYn>N</centerYn><districtCd>2</districtCd><regionName>성남</regionName><stationId>277103679</stationId><stationName>금토JC(경유)</stationName><x>127.0853167</x><y>37.4152833</y><stationSeq>15</stationSeq><turnYn>N</turnYn></busRouteStationList><busRouteStationList><centerYn>N</centerYn><districtCd>2</districtCd><regionName>서울</regionName><stationId>277103441</stationId><stationName>서울진입(경유)</stationName><x>127.0665833</x><y>37.43385</y><stationSeq>16</stationSeq><turnYn>N</turnYn></busRouteStationList><busRouteStationList><centerYn>N</centerYn><districtCd>2</districtCd><regionName>서울</regionName><stationId>277104177</stationId><stationName>청계산입구역(경유)</stationName><x>127.0542</x><y>37.4483667</y><stationSeq>17</stationSeq><turnYn>N</turnYn></busRouteStationList><busRouteStationList><centerYn>N</centerYn><districtCd>2</districtCd><regionName>서울</regionName><stationId>277103388</stationId><stationName>양재IC(경유)</stationName><x>127.04045</x><y>37.4632833</y><stationSeq>18</stationSeq><turnYn>N</turnYn></busRouteStationList><busRouteStationList><centerYn>N</centerYn><districtCd>2</districtCd><regionName>서울</regionName><stationId>277103390</stationId><stationName>서초IC(경유)</stationName><x>127.0263333</x><y>37.4831333</y><stationSeq>19</stationSeq><turnYn>N</turnYn></busRouteStationList><busRouteStationList><centerYn>N</centerYn><districtCd>2</districtCd><regionName>서울</regionName><stationId>277103391</stationId><stationName>반포IC(경유)</stationName><x>127.0188667</x><y>37.50285</y><stationSeq>20</stationSeq><turnYn>N</turnYn></busRouteStationList><busRouteStationList><centerYn>N</centerYn><districtCd>2</districtCd><regionName>서울</regionName><stationId>277103400</stationId><stationName>한남IC(경유)</stationName><x>127.0175833</x><y>37.5224833</y><stationSeq>21</stationSeq><turnYn>N</turnYn></busRouteStationList><busRouteStationList><centerYn>N</centerYn><districtCd>2</districtCd><regionName>서울</regionName><stationId>277104180</stationId><stationName>한남1고가차도(경유)</stationName><x>127.0026333</x><y>37.5414667</y><stationSeq>22</stationSeq><turnYn>N</turnYn></busRouteStationList><busRouteStationList><centerYn>N</centerYn><districtCd>2</districtCd><regionName>서울</regionName><stationId>277104186</stationId><stationName>남산1호터널TG(경유)</stationName><x>126.99315</x><y>37.55585</y><stationSeq>23</stationSeq><turnYn>N</turnYn></busRouteStationList><busRouteStationList><centerYn>Y</centerYn><districtCd>2</districtCd><regionName>서울</regionName><stationId>101000002</stationId><stationName>서울백병원.국가인권위.안중근활동터(중)</stationName><x>126.98785</x><y>37.5643167</y><stationSeq>24</stationSeq><turnYn>N</turnYn></busRouteStationList><busRouteStationList><centerYn>N</centerYn><districtCd>2</districtCd><regionName>서울</regionName><stationId>101000303</stationId><stationName>서울시청</stationName><x>126.9807667</x><y>37.56615</y><stationSeq>25</stationSeq><turnYn>N</turnYn></busRouteStationList><busRouteStationList><centerYn>N</centerYn><districtCd>2</districtCd><regionName>서울</regionName><stationId>277104283</stationId><stationName>시청교차로(경유)</stationName><x>126.9767667</x><y>37.56455</y><stationSeq>26</stationSeq><turnYn>N</turnYn></busRouteStationList><busRouteStationList><centerYn>N</centerYn><districtCd>2</districtCd><regionName>서울</regionName><stationId>101000128</stationId><stationName>신한은행본점</stationName><x>126.9755167</x><y>37.5611167</y><stationSeq>27</stationSeq><turnYn>N</turnYn></busRouteStationList><busRouteStationList><centerYn>Y</centerYn><districtCd>2</districtCd><regionName>서울</regionName><stationId>101000008</stationId><stationName>숭례문(중)</stationName><x>126.9736833</x><y>37.5584667</y><stationSeq>28</stationSeq><turnYn>N</turnYn></busRouteStationList><busRouteStationList><centerYn>Y</centerYn><districtCd>2</districtCd><regionName>서울</regionName><stationId>101000006</stationId><stationName>서울역버스환승센터(6번승강장)(중)</stationName><x>126.97285</x><y>37.5555167</y><stationSeq>29</stationSeq><turnYn>Y</turnYn></busRouteStationList><busRouteStationList><centerYn>N</centerYn><districtCd>2</districtCd><regionName>서울</regionName><stationId>277101742</stationId><stationName>서울역교차로(경유)</stationName><x>126.9726333</x><y>37.5571</y><stationSeq>30</stationSeq><turnYn>N</turnYn></busRouteStationList><busRouteStationList><centerYn>N</centerYn><districtCd>2</districtCd><regionName>서울</regionName><stationId>277102115</stationId><stationName>숭례문교차로(경유)</stationName><x>126.9754333</x><y>37.5603667</y><stationSeq>31</stationSeq><turnYn>N</turnYn></busRouteStationList><busRouteStationList><centerYn>N</centerYn><districtCd>2</districtCd><regionName>서울</regionName><stationId>277102114</stationId><stationName>남대문로3가(경유)</stationName><x>126.9789833</x><y>37.56105</y><stationSeq>32</stationSeq><turnYn>N</turnYn></busRouteStationList><busRouteStationList><centerYn>N</centerYn><districtCd>2</districtCd><regionName>서울</regionName><stationId>101000148</stationId><stationName>명동국민은행앞</stationName><x>126.9826</x><y>37.5646833</y><stationSeq>33</stationSeq><turnYn>N</turnYn></busRouteStationList><busRouteStationList><centerYn>Y</centerYn><districtCd>2</districtCd><regionName>서울</regionName><stationId>101000001</stationId><stationName>남대문세무서.서울백병원(중)</stationName><x>126.9875333</x><y>37.5649667</y><stationSeq>34</stationSeq><turnYn>N</turnYn></busRouteStationList><busRouteStationList><centerYn>N</centerYn><districtCd>2</districtCd><regionName>서울</regionName><stationId>277104181</stationId><stationName>남산1호터널TG(경유)</stationName><x>126.9927167</x><y>37.5557</y><stationSeq>35</stationSeq><turnYn>N</turnYn></busRouteStationList><busRouteStationList><centerYn>N</centerYn><districtCd>2</districtCd><regionName>서울</regionName><stationId>277104179</stationId><stationName>한남1고가차도(경유)</stationName><x>127.0024833</x><y>37.5413333</y><stationSeq>36</stationSeq><turnYn>N</turnYn></busRouteStationList><busRouteStationList><centerYn>N</centerYn><districtCd>2</districtCd><regionName>서울</regionName><stationId>277103399</stationId><stationName>한남IC(경유)</stationName><x>127.0172833</x><y>37.5220333</y><stationSeq>37</stationSeq><turnYn>N</turnYn></busRouteStationList><busRouteStationList><centerYn>N</centerYn><districtCd>2</districtCd><regionName>서울</regionName><stationId>277103392</stationId><stationName>반포IC(경유)</stationName><x>127.0184333</x><y>37.5028167</y><stationSeq>38</stationSeq><turnYn>N</turnYn></busRouteStationList><busRouteStationList><centerYn>N</centerYn><districtCd>2</districtCd><regionName>서울</regionName><stationId>277103389</stationId><stationName>서초IC(경유)</stationName><x>127.0256667</x><y>37.48365</y><stationSeq>39</stationSeq><turnYn>N</turnYn></busRouteStationList><busRouteStationList><centerYn>N</centerYn><districtCd>2</districtCd><regionName>서울</regionName><stationId>277103387</stationId><stationName>양재IC(경유)</stationName><x>127.0394333</x><y>37.46365</y><stationSeq>40</stationSeq><turnYn>N</turnYn></busRouteStationList><busRouteStationList><centerYn>N</centerYn><districtCd>2</districtCd><regionName>서울</regionName><stationId>277104178</stationId><stationName>청계산입구역(경유)</stationName><x>127.0538333</x><y>37.4481833</y><stationSeq>41</stationSeq><turnYn>N</turnYn></busRouteStationList><busRouteStationList><centerYn>N</centerYn><districtCd>2</districtCd><regionName>성남</regionName><stationId>277103678</stationId><stationName>금토JC(경유)</stationName><x>127.08445</x><y>37.4155</y><stationSeq>42</stationSeq><turnYn>N</turnYn></busRouteStationList><busRouteStationList><centerYn>N</centerYn><districtCd>2</districtCd><regionName>성남</regionName><stationId>277103150</stationId><stationName>판교IC(경유)</stationName><x>127.10005</x><y>37.3988333</y><stationSeq>43</stationSeq><turnYn>N</turnYn></busRouteStationList><busRouteStationList><centerYn>N</centerYn><districtCd>2</districtCd><regionName>성남</regionName><stationId>277103385</stationId><stationName>서울TG(경유)</stationName><x>127.1026</x><y>37.36535</y><stationSeq>44</stationSeq><turnYn>N</turnYn></busRouteStationList><busRouteStationList><centerYn>N</centerYn><districtCd>2</districtCd><regionName>용인</regionName><stationId>277103442</stationId><stationName>죽전(경유)</stationName><x>127.10315</x><y>37.3266</y><stationSeq>45</stationSeq><turnYn>N</turnYn></busRouteStationList><busRouteStationList><centerYn>N</centerYn><districtCd>2</districtCd><regionName>수원</regionName><stationId>277103692</stationId><stationName>광교(경유)</stationName><x>127.07955</x><y>37.2933833</y><stationSeq>46</stationSeq><turnYn>N</turnYn></busRouteStationList><busRouteStationList><centerYn>N</centerYn><districtCd>2</districtCd><regionName>수원</regionName><stationId>277103381</stationId><stationName>동수원TG(경유)</stationName><x>127.0475</x><y>37.29805</y><stationSeq>47</stationSeq><turnYn>N</turnYn></busRouteStationList><busRouteStationList><centerYn>N</centerYn><districtCd>2</districtCd><mobileNo> 04185</mobileNo><regionName>수원</regionName><stationId>203000041</stationId><stationName>차세대융합기술연구원.푸르지오월드마크</stationName><x>127.04785</x><y>37.2934</y><stationSeq>48</stationSeq><turnYn>N</turnYn></busRouteStationList><busRouteStationList><centerYn>N</centerYn><districtCd>2</districtCd><mobileNo> 04397</mobileNo><regionName>수원</regionName><stationId>203000400</stationId><stationName>광교중앙.아주대역환승센터</stationName><x>127.0516333</x><y>37.2883167</y><stationSeq>49</stationSeq><turnYn>N</turnYn></busRouteStationList><busRouteStationList><centerYn>N</centerYn><districtCd>2</districtCd><mobileNo> 04284</mobileNo><regionName>수원</regionName><stationId>203000295</stationId><stationName>소화초등학교</stationName><x>127.0516167</x><y>37.27825</y><stationSeq>50</stationSeq><turnYn>N</turnYn></busRouteStationList><busRouteStationList><centerYn>N</centerYn><districtCd>2</districtCd><mobileNo> 04058</mobileNo><regionName>수원</regionName><stationId>203000177</stationId><stationName>KT동수원지사</stationName><x>127.0514</x><y>37.2732</y><stationSeq>51</stationSeq><turnYn>N</turnYn></busRouteStationList><busRouteStationList><centerYn>N</centerYn><districtCd>2</districtCd><mobileNo> 04086</mobileNo><regionName>수원</regionName><stationId>203000175</stationId><stationName>광교호수공원입구.원천교사거리</stationName><x>127.0590333</x><y>37.2707667</y><stationSeq>52</stationSeq><turnYn>N</turnYn></busRouteStationList><busRouteStationList><centerYn>N</centerYn><districtCd>2</districtCd><mobileNo> 04073</mobileNo><regionName>수원</regionName><stationId>203000083</stationId><stationName>금성아파트.한국1차아파트</stationName><x>127.0567167</x><y>37.2680333</y><stationSeq>53</stationSeq><turnYn>N</turnYn></busRouteStationList><busRouteStationList><centerYn>N</centerYn><districtCd>2</districtCd><mobileNo> 04045</mobileNo><regionName>수원</regionName><stationId>203000028</stationId><stationName>삼성전자중앙문</stationName><x>127.0480833</x><y>37.2592333</y><stationSeq>54</stationSeq><turnYn>N</turnYn></busRouteStationList></msgBody></response>